powfacpy/__init__.py
powfacpy/engineering_helpers.py
powfacpy/exceptions.py
powfacpy/pf_class_protocols.py
powfacpy/pf_elm_objects.py
powfacpy/result_variables.py
powfacpy/result_variables_parser.py
powfacpy/applications/__init__.py
powfacpy/applications/application_base.py
powfacpy/applications/caching.py
powfacpy/applications/database - Copy.py
powfacpy/applications/database.py
powfacpy/applications/dynamic_model_docs.py
powfacpy/applications/dynamic_simulation.py
powfacpy/applications/model_exchange.py
powfacpy/applications/networks.py
powfacpy/applications/pandapower_interface.py
powfacpy/applications/pandas_interface.py
powfacpy/applications/plots.py
powfacpy/applications/results.py
powfacpy/applications/static_calc.py
powfacpy/applications/study_cases.py
powfacpy/applications/topology.py
powfacpy/base/__init__.py
powfacpy/base/active_project.py
powfacpy/base/base.py
powfacpy/base/folder.py
powfacpy/base/functional.py
powfacpy/base/string_manipulation.py
powfacpy/deprecated/active_project_interface.py
powfacpy/deprecated/case_studies.py
powfacpy/deprecated/database_interface.py
powfacpy/deprecated/dyn_sim_interface.py
powfacpy/deprecated/folders_interface.py
powfacpy/deprecated/model_exchange_interfaces.py
powfacpy/deprecated/network_interface.py
powfacpy/deprecated/plot_interface.py
powfacpy/deprecated/results_interface.py
powfacpy/deprecated/script_interface.py
powfacpy/pf_classes/__init__.py
powfacpy/pf_classes/protocol_generator.py
powfacpy/pf_classes/protocols.py
powfacpy/pf_classes/blk/definition.py
powfacpy/pf_classes/blk/slot.py
powfacpy/pf_classes/elm/__init__.py
powfacpy/pf_classes/elm/area.py
powfacpy/pf_classes/elm/boundary.py
powfacpy/pf_classes/elm/comp.py
powfacpy/pf_classes/elm/dsl.py
powfacpy/pf_classes/elm/elm_base.py
powfacpy/pf_classes/elm/file.py
powfacpy/pf_classes/elm/grouping_base.py
powfacpy/pf_classes/elm/sym.py
powfacpy/pf_classes/elm/term.py
powfacpy/pf_classes/elm/zone.py
powfacpy/pf_classes/set/__init__.py
powfacpy-0.4.0.dist-info/METADATA
powfacpy-0.4.0.dist-info/WHEEL
powfacpy-0.4.0.dist-info/licenses/LICENSE
powfacpy-0.4.0.dist-info/RECORD
