Metadata-Version: 2.4
Name: powfacpy
Version: 0.4.0
Summary: PowerFactory wrapper
Project-URL: Homepage, https://github.com/FraunhIEE-UniKassel-PowSysStability/powfacpy
Project-URL: Bug Tracker, https://github.com/FraunhIEE-UniKassel-PowSysStability/powfacpy/issues
Author-email: Sciemon <simon.eberlein@gmx.de>
License: Copyright (c) 2018 The Python Packaging Authority
License-File: LICENSE
Classifier: License :: OSI Approved :: MIT License
Classifier: Operating System :: OS Independent
Classifier: Programming Language :: Python :: 3
Requires-Python: >=3.10
Requires-Dist: aenum>=3.1.15
Requires-Dist: comtraderecord>=1.0.2
Requires-Dist: icecream>=2.1.3
Requires-Dist: matplotlib>=3.8.4
Requires-Dist: pandapower==3.2
Requires-Dist: pandas>=2.2.2
